{"_id": "573a139af29313caabcef061", "awards": {"nominations": 10, "text": "7 wins & 10 nominations.", "wins": 7}, "cast": ["Javier Bardem", "Aitana S\u00e8nchez-Gij\u00e8n", "Josep Maria Flotats", "Mar\u00e8a Barranco"], "countries": ["Spain"], "directors": ["Manuel G\u00e8mez Pereira"], "fullplot": "For financial reasons an unemployed aspiring actor works for a phone-sex enterprise. One day he receives a call from the mysterious wife of one of his best clients.", "genres": ["Comedy", "Romance"], "imdb": {"id": 112546, "rating": 6.6, "votes": 1265}, "languages": ["Spanish", "English"], "lastupdated": "2015-09-12 00:38:42.757000000", "num_mflix_comments": 1, "plot": "For financial reasons an unemployed aspiring actor works for a phone-sex enterprise. One day he receives a call from the mysterious wife of one of his best clients.", "poster": "https://m.media-amazon.com/images/M/MV5BZjgwYjhiOTUtNzQzZS00Zjg1LWIyOWEtM2RmOTBlZTNiY2E2XkEyXkFqcGdeQXVyMTA0MjU0Ng@@._V1_SY1000_SX677_AL_.jpg", "rated": "R", "released": 873417600000, "runtime": 106, "title": "Mouth to Mouth", "tomatoes": {"critic": {"meter": 33, "numReviews": 9, "rating": 5.8}, "dvd": 1062460800000, "fresh": 3, "lastUpdated": 1437767534000, "rotten": 6, "viewer": {"meter": 50, "numReviews": 369, "rating": 3.3}}, "type": "movie", "writers": ["Manuel G\u00e8mez Pereira (dialogue)", "Juan Luis Iborra", "Joaqu\u00e8n Oristrell", "Naomi Wise"], "year": 1995}