{"_id": "573a13b0f29313caabd340dd", "awards": {"nominations": 7, "text": "Nominated for 1 Primetime Emmy. Another 7 wins & 7 nominations.", "wins": 8}, "cast": ["Shawn Ashmore"], "countries": ["USA", "Canada"], "fullplot": "A reckless youth is destined to become the greatest sorcerer that the mystical land of Earthsea has ever known. When the young wizard Ged discovers that he possesses infinite magical powers, he seeks to master the ancient arts. As he journeys to manhood, he will combat dragons, fall in love, cross death's threshold, and ultimately wield the power to reunite a kingdom.", "genres": ["Fantasy", "Drama", "Adventure"], "imdb": {"id": 407384, "rating": 5.7, "votes": 5064}, "languages": ["English"], "lastupdated": "2015-08-29 00:50:26.813000000", "num_mflix_comments": 1, "plot": "A reckless youth is destined to become the greatest sorcerer that the mystical land of Earthsea has ever known. When the young wizard Ged discovers that he possesses infinite magical powers...", "poster": "https://m.media-amazon.com/images/M/MV5BMTk0MjY2NTEyMV5BMl5BanBnXkFtZTcwMDMzMzcyMQ@@._V1_SY1000_SX677_AL_.jpg", "released": 1102896000000, "runtime": 90, "title": "Earthsea", "tomatoes": {"dvd": 1110240000000, "lastUpdated": 1441133643000, "viewer": {"meter": 52, "numReviews": 8088, "rating": 3.2}}, "type": "movie", "year": 2004}