{"_id": "573a1396f29313caabce34c9", "awards": {"nominations": 0, "text": "Won 1 BAFTA Film Award. Another 1 win.", "wins": 2}, "cast": ["Albert Finney", "Colin Blakely", "Billie Whitelaw", "Liza Minnelli"], "countries": ["UK"], "directors": ["Albert Finney"], "fullplot": "Charlie Bubbles, a writer, up from the working class of Manchester, England, who, in the course of becoming prematurely rich and famous, has mislaid a writer's basic tool - the capacity to feel and to respond. Now he must visit his estranged wife and son, whom he has set up on a farm outside his native city. His journey accidentally becomes an attempt to reestablish his connections with life, people, and his own history.", "genres": ["Comedy", "Drama"], "imdb": {"id": 62792, "rating": 6.5, "votes": 392}, "languages": ["English"], "lastupdated": "2015-09-03 01:17:13.507000000", "plot": "A married writer has an affair with his secretary.", "poster": "https://m.media-amazon.com/images/M/MV5BZDg4N2VjZTgtNjBlNS00MjY3LTg1MWItMTVlNDQ4MTNkYTAyXkEyXkFqcGdeQXVyMjI4MjA5MzA@._V1_SY1000_SX677_AL_.jpg", "released": -59616000000, "runtime": 89, "title": "Charlie Bubbles", "tomatoes": {"lastUpdated": 1441997420000, "viewer": {"meter": 75, "numReviews": 110, "rating": 3.3}}, "type": "movie", "writers": ["Shelagh Delaney"], "year": 1967}