{"_id": "573a13cff29313caabd8981f", "awards": {"nominations": 2, "text": "2 nominations.", "wins": 0}, "cast": ["Mimi Chakarova"], "countries": ["USA", "United Arab Emirates", "Bulgaria", "Moldova", "Turkey"], "directors": ["Mimi Chakarova"], "fullplot": "A documentary about young Eastern European women who've been drawn into a netherworld of sex trafficking and abuse. It is a story told by survivors; a film that gives a voice to women who were supposed to be silenced by shame, fear and intimidation. Mimi Chakarova, a photojournalist who grew up in Bulgaria, takes us on a personal, investigative journey into the shadowy world of sex trafficking from Eastern Europe to Turkey, Dubai and Greece. Told through the personal accounts of trafficked women, undercover footage, and still photography, this documentary exposes the root causes of why women continue to be sold into prostitution against their will and examines what can be done to stop it.", "genres": ["Documentary", "Crime", "Drama"], "imdb": {"id": 1734163, "rating": 7.5, "votes": 104}, "languages": ["English", "Turkish", "Romanian"], "lastupdated": "2015-07-04 00:02:54.667000000", "num_mflix_comments": 2, "plot": "A documentary about young Eastern European women who've been drawn into a netherworld of sex trafficking and abuse. It is a story told by survivors; a film that gives a voice to women who ...", "released": 1302307200000, "runtime": 72, "title": "The Price of Sex", "tomatoes": {"lastUpdated": 1420414981000, "viewer": {"numReviews": 0, "rating": 0}, "website": "http://www.neasahardiman.com/"}, "type": "movie", "year": 2011}