{"_id": "573a139ef29313caabcfbc0e", "awards": {"nominations": 30, "text": "Nominated for 1 Oscar. Another 18 wins & 30 nominations.", "wins": 19}, "cast": ["Sissy Spacek", "Jane Galloway Heitz", "Joseph A. Carpenter", "Donald Wiegert"], "countries": ["France", "UK", "USA"], "directors": ["David Lynch"], "fullplot": "\"The Straight Story\" chronicles a trip made by 73-year-old Alvin Straight from Laurens, Iowa, to Mt. Zion, Wis., in 1994 while riding a lawn mower. The man undertook his strange journey to mend his relationship with his ill, estranged, 75-year-old brother Lyle.", "genres": ["Biography", "Drama"], "imdb": {"id": 166896, "rating": 8, "votes": 60487}, "languages": ["English"], "lastupdated": "2015-09-17 04:46:55.560000000", "metacritic": 86, "num_mflix_comments": 2, "plot": "An old man makes a long journey by lawn-mover tractor to mend his relationship with an ill brother.", "poster": "https://m.media-amazon.com/images/M/MV5BNmE1MDk4OWEtYjk1NS00MWU2LTk5ZWItYjZhYmRkODRjMDc0XkEyXkFqcGdeQXVyNjE5MjUyOTM@._V1_SY1000_SX677_AL_.jpg", "rated": "G", "released": 941587200000, "runtime": 112, "title": "The Straight Story", "tomatoes": {"consensus": "Slow-paced but heart-warming.", "critic": {"meter": 96, "numReviews": 89, "rating": 8.1}, "dvd": 973555200000, "fresh": 85, "lastUpdated": 1441991259000, "production": "Buena Vista Pictures", "rotten": 4, "viewer": {"meter": 91, "numReviews": 30624, "rating": 4}, "website": "http://disney.go.com/DisneyPictures/straightstory/index.html"}, "type": "movie", "writers": ["John Roach", "Mary Sweeney"], "year": 1999}