{"_id": "573a1397f29313caabce6bc0", "awards": {"nominations": 0, "text": "1 win.", "wins": 1}, "cast": ["Ab Abspoel", "Adriaan Adriaanse", "Harry Bas", "Tim Beekman"], "countries": ["Netherlands", "Belgium"], "directors": ["Guido Pieters"], "fullplot": "Doctor Vlimmen, the nearest Dutch equivalent to All Creatures Great and Small, is about the competent veterinarian of that name in the Dutch countryside, whose modern methods, liberal opinions and private life are considered scandalous by many of the conservative-Christian peasants. His socially more acceptable colleague Dr. Treeborg, who cares less for the animals and their rather poor owners, is thus more likely to be appointed at the public slaughterhouse and thus made untouchable, and both vets prepare legal action against each-other, thus involving Vlimmens only friend, a lawyer with whom he regularly visits Antwerp.", "genres": ["Drama"], "imdb": {"id": 77449, "rating": 6.1, "votes": 179}, "languages": ["Dutch"], "lastupdated": "2015-09-16 00:21:26.677000000", "plot": "Doctor Vlimmen, the nearest Dutch equivalent to All Creatures Great and Small, is about the competent veterinarian of that name in the Dutch countryside, whose modern methods, liberal ...", "released": 225504000000, "runtime": 107, "title": "Doctor Vlimmen", "tomatoes": {"dvd": 1112054400000, "lastUpdated": 1440614933000, "viewer": {"meter": 26, "numReviews": 101, "rating": 2.6}}, "type": "movie", "writers": ["Guido Pieters", "Ben Verbong", "A. Roothaert (novel)"], "year": 1977}