{"_id": "573a1398f29313caabce9e72", "awards": {"nominations": 0, "text": "1 win.", "wins": 1}, "cast": ["John Cleese", "Penny Leatherbarrow", "Howard Lloyd-Lewis", "Jonathan Bowater"], "countries": ["UK"], "directors": ["Christopher Morahan"], "fullplot": "Brian Stimpson is the headmaster of a comprehensive (high) school in England. He sets himself, his staff and pupils very high standards. On the way to a conference at which he is to talk, all manner of disasters strike.", "genres": ["Comedy"], "imdb": {"id": 90852, "rating": 6.6, "votes": 8679}, "languages": ["English"], "lastupdated": "2015-08-18 00:21:37.563000000", "num_mflix_comments": 1, "plot": "An uncompromising British school headmaster finds himself beset by one thing going wrong after another.", "poster": "https://m.media-amazon.com/images/M/MV5BMTQ4MDU1ODk5M15BMl5BanBnXkFtZTYwMzI2OTk4._V1_SY1000_SX677_AL_.jpg", "rated": "PG", "released": 529286400000, "runtime": 96, "title": "Clockwise", "type": "movie", "writers": ["Michael Frayn (original screenplay)"], "year": 1986}