{"_id": "573a139af29313caabcf1ac7", "awards": {"nominations": 1, "text": "1 win & 1 nomination.", "wins": 1}, "cast": ["Kim Jensen", "Allan Olsen", "Helle Nielsen", "Ghita N\u00e8rby"], "countries": ["Denmark"], "directors": ["Morten Arnfred", "Henning Kristiansen"], "fullplot": "Youth film about friendship between two boys from very different backgrounds. Steffen finish school and do not really know what he wants. He lives at home with his mother, who is a journalist. He comes with Majbritt, the daughter of one of the rich men in Silkeborg, where the story takes place. Charly is a Copenhagen mess already know life's dark sides and is placed in a youth home outside the city. They meet when Charly is by cutting Steffens moped. As the story concludes, the Charly again got mixed up in something and have to run away, and now gives Steffen him the moped. They have become friends, and the friendship has also been shown to outweigh Steffens compared to Majbritt and the upper class, she represents.", "genres": ["Drama"], "imdb": {"id": 124002, "rating": 6.4, "votes": 274}, "languages": ["Danish"], "lastupdated": "2015-08-29 00:06:47.513000000", "num_mflix_comments": 1, "plot": "Youth film about friendship between two boys from very different backgrounds. Steffen finish school and do not really know what he wants. He lives at home with his mother, who is a ...", "released": 259113600000, "runtime": 98, "title": "Me and Charly", "tomatoes": {"dvd": 896140800000, "lastUpdated": 1433445830000, "viewer": {"numReviews": 4, "rating": 0}}, "type": "movie", "writers": ["Morten Arnfred", "Henning Kristiansen", "Bent E. Rasmussen (novel)"], "year": 1978}