{"_id": "573a13a7f29313caabd1bb67", "awards": {"nominations": 5, "text": "Nominated for 2 Primetime Emmys. Another 3 nominations.", "wins": 0}, "cast": ["Bob Hoskins", "James Fox", "Tom Ward", "Matthew Rhys"], "countries": ["UK", "USA", "Germany"], "directors": ["Stuart Orme"], "fullplot": "Professor Challenger reveals the existence of a remote plateau in the Amazon jungle where dinosaurs have survived. He returns there leading an expedition. Not only are dinosaurs found and confronted, but also highly evolved apes, Amazonian Indians who think Challenger a god, and, on the way, the attractive orphaned niece of a lonely missionary. Theology intervenes in this exercise in vindicating Darwin and the missionary twice attempts to sabotage the mission. After much excitement, love is found in unexpected places, and, confronted by civilization, as represented by the Royal Society in London, Challenger changes his story.", "genres": ["Adventure", "Drama", "Fantasy"], "imdb": {"id": 302739, "rating": 6.7, "votes": 2257}, "languages": ["English"], "lastupdated": "2015-08-25 00:12:16.213000000", "num_mflix_comments": 2, "plot": "An expedition leaves for the Amazon to prove the existance of dinosaurs.", "poster": "https://m.media-amazon.com/images/M/MV5BMTIwMjY1MzI2M15BMl5BanBnXkFtZTYwODg5MDk4._V1_SY1000_SX677_AL_.jpg", "released": 1033862400000, "runtime": 150, "title": "The Lost World", "tomatoes": {"dvd": 1035849600000, "lastUpdated": 1441993113000, "production": "A & E", "viewer": {"meter": 55, "numReviews": 645, "rating": 3.3}, "website": "http://www.bbc.co.uk/drama/lostworld"}, "type": "movie", "writers": ["Arthur Conan Doyle (novel)", "Adrian Hodges", "Tony Mulholland (dramatist)"], "year": 2001}