{"_id": "573a13c0f29313caabd60fca", "awards": {"nominations": 4, "text": "5 wins & 4 nominations.", "wins": 5}, "cast": ["Louis Koo", "Barbie Hsu", "Nick Cheung", "Ye Liu"], "countries": ["China", "Hong Kong"], "directors": ["Benny Chan"], "fullplot": "A man receives a distressing phone call from a woman who has been kidnapped.", "genres": ["Action"], "imdb": {"id": 1156506, "rating": 6.7, "votes": 1438}, "languages": ["Cantonese", "Mandarin", "English"], "lastupdated": "2015-09-01 00:47:04.990000000", "plot": "A man receives a distressing phone call from a woman who has been kidnapped.", "poster": "https://m.media-amazon.com/images/M/MV5BNGI5MTFjYTktYjA2Mi00MDc3LTg2ZmYtNDNkMzcxMTg4NzUyXkEyXkFqcGdeQXVyMTQ3Njg3MQ@@._V1_SY1000_SX677_AL_.jpg", "released": 1222300800000, "runtime": 110, "title": "Connected", "tomatoes": {"dvd": 1232409600000, "lastUpdated": 1441131547000, "production": "Emperor Motion Pictures", "viewer": {"meter": 74, "numReviews": 1784, "rating": 3.6}, "website": "http://connected.emp.hk/"}, "type": "movie", "writers": ["Alan Yuen (screenplay)", "Benny Chan (screenplay)", "Bing Xu (screenplay)", "Larry Cohen (original story)", "Chris Morgan"], "year": 2008}