{"_id": "573a1396f29313caabce4a26", "awards": {"nominations": 0, "text": "2 wins.", "wins": 2}, "cast": ["Cantinflas", "Fernando Fern\u00e8n G\u00e8mez", "Mar\u00e8a Fernanda D'Oc\u00e8n", "Paca Gabald\u00e8n"], "countries": ["Spain", "Mexico"], "directors": ["Roberto Gavald\u00e8n"], "genres": ["Comedy"], "imdb": {"id": 68496, "rating": 6.7, "votes": 99}, "languages": ["Spanish"], "lastupdated": "2015-06-27 00:06:26.030000000", "num_mflix_comments": 1, "released": 100483200000, "runtime": 132, "title": "Don Quijote cabalga de nuevo", "tomatoes": {"lastUpdated": 1434306662000, "viewer": {"numReviews": 3, "rating": 4}}, "type": "movie", "writers": ["Carlos Blanco (screenplay)", "Carlos Blanco (story)", "Miguel de Cervantes y Saavedra (novel)"], "year": 1973}