{"_id": "573a1398f29313caabcebd8d", "awards": {"nominations": 5, "text": "1 win & 5 nominations.", "wins": 1}, "cast": ["Tom Hanks", "Bruce Willis", "Melanie Griffith", "Kim Cattrall"], "countries": ["USA"], "directors": ["Brian De Palma"], "fullplot": "Financial \"Master of the Universe\" Sherman McCoy sees his life unravel when his mistress Maria Ruskin hits a black boy with his car. When yellow journalist Peter Fallow enflames public opinion with a series of distorted tabloid articles on the accident, the case is seized upon by opportunists like Reverend Bacon and mayoral candidate D.A. Abe Weiss.", "genres": ["Comedy", "Drama"], "imdb": {"id": 99165, "rating": 5.4, "votes": 16807}, "languages": ["English"], "lastupdated": "2015-08-30 00:43:37.993000000", "num_mflix_comments": 1, "plot": "After his mistress runs over a young teen, a Wall Street hotshot sees his life unravel in the spotlight, and attracting the interest of a down and out reporter.", "poster": "https://m.media-amazon.com/images/M/MV5BMTc4MzEzMjc0Nl5BMl5BanBnXkFtZTgwNzU1NTk4NjE@._V1_SY1000_SX677_AL_.jpg", "rated": "R", "released": 661737600000, "runtime": 125, "title": "The Bonfire of the Vanities", "tomatoes": {"critic": {"meter": 16, "numReviews": 50, "rating": 3.9}, "dvd": 1005004800000, "fresh": 8, "lastUpdated": 1440271320000, "production": "Warner Home Video", "rotten": 42, "viewer": {"meter": 27, "numReviews": 11988, "rating": 2.6}}, "type": "movie", "writers": ["Michael Cristofer (screenplay)", "Tom Wolfe (novel)"], "year": 1990}