{"_id": "573a13f5f29313caabde398f", "awards": {"nominations": 1, "text": "14 wins & 1 nomination.", "wins": 14}, "cast": ["Winona Mae", "Julia Pott"], "countries": ["USA"], "directors": ["Don Hertzfeldt"], "fullplot": "A little girl is taken on a mind-bending tour of her distant future.", "genres": ["Animation", "Short", "Comedy"], "imdb": {"id": 4171032, "rating": 8.3, "votes": 626}, "languages": ["English"], "lastupdated": "2015-09-07 00:55:54.677000000", "plot": "A little girl is taken on a mind-bending tour of her distant future.", "released": 1427760000000, "runtime": 17, "title": "World of Tomorrow", "type": "movie", "writers": ["Don Hertzfeldt"], "year": 2015}