{"_id": "573a13bdf29313caabd58675", "awards": {"nominations": 1, "text": "1 win & 1 nomination.", "wins": 1}, "cast": ["Phillip Adams", "Glory Annen", "Christine Amor", "Victoria Anoux"], "countries": ["Australia", "USA"], "directors": ["Mark Hartley"], "fullplot": "The story of \"Ozploitation\" movies - a time when Australian cinema showed an explosion of sex, violence, horror and action. Includes anecdotes, lessons in maverick filmmaking and a genuine love of Australian movies. It moves through Aussie genre cinema of the 70s and early 80s - claiming it's an unjustly forgotten cinematic era of boobs, pubes, tubes... and even a little kung fu.", "genres": ["Documentary"], "imdb": {"id": 996966, "rating": 7.7, "votes": 2967}, "languages": ["English"], "lastupdated": "2015-09-06 01:02:16.977000000", "metacritic": 76, "num_mflix_comments": 2, "plot": "The story of the Australian exploitation genre cinema of 1970s and 80s.", "poster": "https://m.media-amazon.com/images/M/MV5BMTg1MjQ1Nzk3Nl5BMl5BanBnXkFtZTcwNjY0NTM5MQ@@._V1_SY1000_SX677_AL_.jpg", "rated": "R", "released": 1219881600000, "runtime": 103, "title": "Not Quite Hollywood: The Wild, Untold Story of Ozploitation!", "tomatoes": {"consensus": "A raucous, fast-paced celebration of the Ozploitation films that came out of Australia in the 1970s and 1980s.", "critic": {"meter": 94, "numReviews": 63, "rating": 7.4}, "dvd": 1254787200000, "fresh": 59, "lastUpdated": 1439836020000, "production": "Magnolia Pictures/Magnet Releasing", "rotten": 4, "viewer": {"meter": 80, "numReviews": 2261, "rating": 3.9}, "website": "http://magnetreleasing.com/notquitehollywood/"}, "type": "movie", "writers": ["Mark Hartley"], "year": 2008}