{"_id": "573a1399f29313caabcecc71", "awards": {"nominations": 6, "text": "Nominated for 1 Golden Globe. Another 9 wins & 6 nominations.", "wins": 10}, "cast": ["Jean-Pierre Marielle", "G\u00e8rard Depardieu", "Anne Brochet", "Guillaume Depardieu"], "countries": ["France"], "directors": ["Alain Corneau"], "fullplot": "It's late 17th century. The viola da gamba player Monsieur de Sainte Colombe comes home to find that his wife died while he was away. In his grief he builds a small house in his garden into which he moves to dedicate his life to music and his two young daughters Madeleine and Toinette, avoiding the outside world. Rumor about him and his music is widespread, and even reaches to the court of Louis XIV, who wants him at his court in Lully's orchestra, but Monsieur de Sainte Colombe refuses. One day a young man, Marin Marais, comes to see him with a request, he wants to be taught how to play the viola.", "genres": ["Biography", "Drama", "Music"], "imdb": {"id": 103110, "rating": 7.5, "votes": 4790}, "languages": ["French"], "lastupdated": "2015-09-10 17:14:04.853000000", "num_mflix_comments": 1, "plot": "It's late 17th century. The viola da gamba player Monsieur de Sainte Colombe comes home to find that his wife died while he was away. In his grief he builds a small house in his garden into...", "poster": "https://m.media-amazon.com/images/M/MV5BMTg1NDU2NDM0OF5BMl5BanBnXkFtZTcwNzQ0NjIzMQ@@._V1_SY1000_SX677_AL_.jpg", "released": 693014400000, "runtime": 115, "title": "Tous les matins du monde", "tomatoes": {"critic": {"meter": 89, "numReviews": 9, "rating": 7.2}, "dvd": 1141689600000, "fresh": 8, "lastUpdated": 1441995648000, "production": "CNC", "rotten": 1, "viewer": {"meter": 89, "numReviews": 4564, "rating": 4.1}}, "type": "movie", "writers": ["Pascal Quignard (based on the novel by)", "Alain Corneau (adaptation)", "Pascal Quignard (adaptation)", "Pascal Quignard (dialogue)"], "year": 1991}