{"_id": "573a13bef29313caabd5c756", "awards": {"nominations": 3, "text": "3 nominations.", "wins": 0}, "cast": ["Nicolas Cage", "Violante Placido", "Ciar\u00e8n Hinds", "Idris Elba"], "countries": ["USA", "United Arab Emirates"], "directors": ["Mark Neveldine", "Brian Taylor"], "fullplot": "Johnny Blaze, a man who made a deal with the Devil who called himself Mephistopheles at the time (now Roarke), is on the run trying to make sure no-one is harmed by his alter ego, The Ghost Rider. He is approached by a Monk named Moreau who tells him that he can help be him free of the Rider, but first, he needs Johnny's help to protect a boy, whom Roarke has plans for, to help him take human form.", "genres": ["Action", "Fantasy", "Thriller"], "imdb": {"id": 1071875, "rating": 4.3, "votes": 80431}, "languages": ["English"], "lastupdated": "2015-09-16 02:17:41.460000000", "metacritic": 32, "num_mflix_comments": 1, "plot": "As Johnny Blaze hides out in Eastern Europe, he is called upon to stop the devil, who is trying to take human form.", "poster": "https://m.media-amazon.com/images/M/MV5BMTkwNDM5MDEzOF5BMl5BanBnXkFtZTcwNDEyNTUxNw@@._V1_SY1000_SX677_AL_.jpg", "rated": "PG-13", "released": 1329436800000, "runtime": 96, "title": "Ghost Rider: Spirit of Vengeance", "tomatoes": {"boxOffice": "$51.8M", "consensus": "With a weak script, uneven CG work, and a Nic Cage performance so predictably loony it's no longer amusing, Ghost Rider: Spirit of Vengeance aims to be trashy fun but ends up as plain trash.", "critic": {"meter": 17, "numReviews": 111, "rating": 3.8}, "dvd": 1339459200000, "fresh": 19, "lastUpdated": 1442079574000, "production": "Sony Pictures", "rotten": 92, "viewer": {"meter": 32, "numReviews": 112032, "rating": 2.6}, "website": "http://www.thespiritofvengeance.com/"}, "type": "movie", "writers": ["Scott M. Gimple (screenplay)", "Seth Hoffman (screenplay)", "David S. Goyer (screenplay)", "David S. Goyer (story)"], "year": 2011}