{"_id": "573a1398f29313caabcea6e9", "awards": {"nominations": 6, "text": "2 wins & 6 nominations.", "wins": 2}, "cast": ["Rachel Ward", "Bryan Brown", "Steven Vidler", "Sam Neill"], "countries": ["Australia"], "directors": ["Ken Cameron"], "fullplot": "In pre-WWII Australia, a love triangle develops between a man, his wife and the man's brother.", "genres": ["Drama"], "imdb": {"id": 93106, "rating": 5.9, "votes": 402}, "languages": ["English"], "lastupdated": "2015-08-23 01:07:03.973000000", "plot": "In pre-WWII Australia, a love triangle develops between a man, his wife and the man's brother.", "poster": "https://m.media-amazon.com/images/M/MV5BZmZmOGE0OTYtMjkyOS00MmRjLTg2ZjAtMmM3NWMzYzc2ODU3XkEyXkFqcGdeQXVyMTMxMTY0OTQ@._V1_SY1000_SX677_AL_.jpg", "rated": "R", "released": 547948800000, "runtime": 98, "title": "Peter Kenna's The Good Wife", "tomatoes": {"dvd": 1009324800000, "lastUpdated": 1439664090000, "viewer": {"meter": 27, "numReviews": 756, "rating": 2.8}}, "type": "movie", "writers": ["Peter Kenna"], "year": 1987}