{"_id": "573a13b4f29313caabd41c04", "awards": {"nominations": 2, "text": "1 win & 2 nominations.", "wins": 1}, "cast": ["Colin Ford", "Joel Gretsch", "Djimon Hounsou", "Dakota Fanning"], "countries": ["USA", "Canada"], "directors": ["Paul McGuigan"], "fullplot": "A group of young American ex-pats with telekinetic and clairvoyant abilities are hiding from a clandestine U.S. government agency. They must utilize their different talents and band together for a final job enabling them to escape the agency forever.", "genres": ["Action", "Sci-Fi", "Thriller"], "imdb": {"id": 465580, "rating": 6.1, "votes": 85694}, "languages": ["English", "Cantonese"], "lastupdated": "2015-09-04 00:28:59.570000000", "metacritic": 36, "num_mflix_comments": 410, "plot": "Two young Americans with special abilities must race to find a girl in Hong Kong before a shadowy government organization called Division does.", "poster": "https://m.media-amazon.com/images/M/MV5BMTM2NjE5NTYzMl5BMl5BanBnXkFtZTcwNzc3OTMyMg@@._V1_SY1000_SX677_AL_.jpg", "rated": "PG-13", "released": 1233878400000, "runtime": 111, "title": "Push", "tomatoes": {"boxOffice": "$31.7M", "consensus": "The sci-fi thriller Push is visually flashy but hyperkinetic and convoluted.", "critic": {"meter": 23, "numReviews": 126, "rating": 4.3}, "dvd": 1246924800000, "fresh": 29, "lastUpdated": 1441909363000, "production": "Summit Entertainment", "rotten": 97, "viewer": {"meter": 42, "numReviews": 2026117, "rating": 2.6}, "website": "http://www.push-themovie.com/"}, "type": "movie", "writers": ["David Bourla"], "year": 2009}