{"_id": "573a13f6f29313caabde5900", "awards": {"nominations": 3, "text": "1 win & 3 nominations.", "wins": 1}, "cast": ["Nadir Saribacak", "Hakan Karsak", "Kadir Cermik", "\u00e8zg\u00e8r Emre Yildirim"], "countries": ["Turkey", "Germany"], "directors": ["Tolga Kara\u00e8elik"], "fullplot": "When the ship's owner goes bankrupt, the crew learns there is a lien on the ship and that key crew members must stay on board. Six men trapped aboard a ship sailing to Egypt.", "genres": ["Drama"], "imdb": {"id": 4309356, "rating": 7.6, "votes": 48}, "languages": ["Turkish"], "lastupdated": "2015-08-05 00:14:34.537000000", "num_mflix_comments": 2, "plot": "When the ship's owner goes bankrupt, the crew learns there is a lien on the ship and that key crew members must stay on board. Six men trapped aboard a ship sailing to Egypt.", "poster": "https://m.media-amazon.com/images/M/MV5BMTUyNzkyNjkwMl5BMl5BanBnXkFtZTgwODM4NzI3NzE@._V1_SY1000_SX677_AL_.jpg", "released": 1422230400000, "runtime": 104, "title": "Ivy", "type": "movie", "writers": ["Tolga Kara\u00e8elik"], "year": 2015}