{"_id": "573a13e6f29313caabdc5503", "awards": {"nominations": 4, "text": "2 wins & 4 nominations.", "wins": 2}, "cast": ["Riccardo Scamarcio", "Sharon Stone", "Cristiana Capotondi", "Giovanna Ralli"], "countries": ["Italy"], "directors": ["Pupi Avati"], "fullplot": "A young copywriter moves to Rome in the wake of his screenwriter father's death, where he meets a publisher who wants to release his dad's autobiography.", "genres": ["Drama"], "imdb": {"id": 3056858, "rating": 5.1, "votes": 128}, "languages": ["Italian"], "lastupdated": "2015-08-14 00:49:44.863000000", "num_mflix_comments": 1, "plot": "A young copywriter moves to Rome in the wake of his screenwriter father's death, where he meets a publisher who wants to release his dad's autobiography.", "released": 1410998400000, "runtime": 102, "title": "Un ragazzo d'oro", "tomatoes": {"lastUpdated": 1442514050000, "viewer": {"numReviews": 2, "rating": 0}}, "type": "movie", "writers": ["Pupi Avati", "Tommaso Avati"], "year": 2014}