{"_id": "573a1398f29313caabcebf94", "awards": {"nominations": 3, "text": "Nominated for 1 Oscar. Another 3 wins & 3 nominations.", "wins": 4}, "cast": ["G\u00e8rard Depardieu", "Andie MacDowell", "Bebe Neuwirth", "Gregg Edelman"], "countries": ["France", "Australia", "USA"], "directors": ["Peter Weir"], "fullplot": "George Faure is a Frenchman who has been offered a job in the U.S. But in order to get the job he must obtain a work permit - green card, and the easiest way is to marry an American. Bronte Parrish is a New Yorker who is a keen horticulturist and just found the perfect flat with its own greenhouse. Unfortunately the flat is for married couples only. A marriage of convenience seems the ideal solution to both problems. To convince the immigration officers they are married for love, they must move in with each other. As the mismatched couple attempt to cope with life together, they start to fall in love.", "genres": ["Comedy", "Drama", "Romance"], "imdb": {"id": 99699, "rating": 6.2, "votes": 17665}, "languages": ["English", "French", "Spanish"], "lastupdated": "2015-09-03 00:58:23.443000000", "metacritic": 58, "num_mflix_comments": 4, "plot": "A man wanting to stay in the US enters into a marriage of convenience, but it turns into more than that.", "poster": "https://m.media-amazon.com/images/M/MV5BMTNjZjQ3MTYtNTdhMS00MDRhLThjMjItMmQ3MzJkMjMyODg5L2ltYWdlL2ltYWdlXkEyXkFqcGdeQXVyNjc1NTYyMjg@._V1_SY1000_SX677_AL_.jpg", "rated": "PG-13", "released": 665366400000, "runtime": 103, "title": "Green Card", "tomatoes": {"critic": {"meter": 56, "numReviews": 18, "rating": 5.5}, "dvd": 1046736000000, "fresh": 10, "lastUpdated": 1442257550000, "production": "Touchstone Pictures", "rotten": 8, "viewer": {"meter": 51, "numReviews": 26192, "rating": 2.8}}, "type": "movie", "writers": ["Peter Weir"], "year": 1990}